aimodeler/__init__.py
aimodeler/cloud_storage.py
aimodeler/file_upload.py
aimodeler/invoke_model.py
aimodeler/text_chunking.py
aimodeler/text_embedding.py
aimodeler/text_extraction.py
aimodeler/vector_storage.py
aimodeler-0.94.dist-info/METADATA
aimodeler-0.94.dist-info/WHEEL
aimodeler-0.94.dist-info/top_level.txt
aimodeler-0.94.dist-info/RECORD
